pyhdfs_client/__init__.py
pyhdfs_client/cli.py
pyhdfs_client/pyhdfs_client.py
pyhdfs_client-0.1.3.dist-info/AUTHORS.rst
pyhdfs_client-0.1.3.dist-info/LICENSE
pyhdfs_client-0.1.3.dist-info/METADATA
pyhdfs_client-0.1.3.dist-info/WHEEL
pyhdfs_client-0.1.3.dist-info/entry_points.txt
pyhdfs_client-0.1.3.dist-info/top_level.txt
pyhdfs_client-0.1.3.dist-info/RECORD
