Metadata-Version: 2.1
Name: pyhdfs-client
Version: 0.1.3
Summary: A py4j based hdfs client for python for native hdfs CLI performance.
Home-page: https://github.com/gupta-paras/pyhdfs_client
Author: Paras Gupta
Author-email: paras_gupta@outlook.com
License: MIT license
Keywords: pyhdfs_client
Platform: UNKNOWN
Classifier: Development Status :: 2 - Pre-Alpha
Classifier: Intended Audience :: Developers
Classifier: License :: OSI Approved :: MIT License
Classifier: Natural Language :: English
Classifier: Programming Language :: Python :: 3
Classifier: Programming Language :: Python :: 3.5
Classifier: Programming Language :: Python :: 3.6
Classifier: Programming Language :: Python :: 3.7
Classifier: Programming Language :: Python :: 3.8
Requires-Python: >=3.5
Requires-Dist: py4j
Requires-Dist: psutil
